README.rst
setup.py
clilabs/__init__.py
clilabs/builtins.py
clilabs/django.py
clilabs/sentry.py
clilabs/test_clilabs.py
clilabs.egg-info/PKG-INFO
clilabs.egg-info/SOURCES.txt
clilabs.egg-info/dependency_links.txt
clilabs.egg-info/entry_points.txt
clilabs.egg-info/requires.txt
clilabs.egg-info/top_level.txt