Metadata-Version: 1.2
Name: clilabs
Version: 1.1.1
Summary: Cheap CLI framework, gives rich commands for Django
Home-page: https://yourlabs.io/oss/clilabs
Author: James Pic
Author-email: jamespic@gmail.com
License: MIT
Keywords: django cli
Platform: UNKNOWN
Classifier: Development Status :: 5 - Production/Stable
Classifier: Environment :: Console
Classifier: Environment :: Plugins
Classifier: Intended Audience :: System Administrators
Classifier: License :: OSI Approved :: MIT License
Classifier: Operating System :: OS Independent
Classifier: Programming Language :: Python :: 3 :: Only
Classifier: Topic :: Database
Classifier: Topic :: Software Development
Classifier: Topic :: System
Classifier: Topic :: Terminals
Requires-Python: >=3
